main.py
mseep_mcp_ai_infra_real_time_agent-0.1.1.dist-info/METADATA
mseep_mcp_ai_infra_real_time_agent-0.1.1.dist-info/WHEEL
mseep_mcp_ai_infra_real_time_agent-0.1.1.dist-info/entry_points.txt
mseep_mcp_ai_infra_real_time_agent-0.1.1.dist-info/top_level.txt
mseep_mcp_ai_infra_real_time_agent-0.1.1.dist-info/RECORD
