Metadata-Version: 2.4
Name: mseep-mcp-ai-infra-real-time-agent
Version: 0.1.1
Summary: Add your description here
Author-email: mseep <support@skydeck.ai>
Requires-Python: >=3.13
Requires-Dist: black>=25.1.0
Requires-Dist: isort>=6.0.1
Requires-Dist: langchain-mcp-adapters>=0.0.7
Requires-Dist: langchain-openai>=0.3.12
Requires-Dist: langgraph>=0.3.29
Requires-Dist: python-dotenv>=1.1.0
